{"nodes": [{"class": 0, "number": 621}, {"class": 1, "number": 92}, {"class": 2, "number": 63}, {"class": 3, "number": 59}, {"class": 4, "number": 52}, {"class": 5, "number": 34}, {"class": 6, "number": 39}, {"class": 7, "number": 2}, {"class": 8, "number": 406}, {"class": 9, "number": 148}, {"class": 10, "number": 96}, {"class": 11, "number": 25}, {"class": 12, "number": 7}], "links": [{"source": 10, "target": 10, "value": 18.65467797973567}, {"source": 10, "target": 9, "value": 17.060400405597232}, {"source": 9, "target": 8, "value": 15.13582950568206}, {"source": 11, "target": 11, "value": 17.600471929225463}, {"source": 11, "target": 10, "value": 17.533306916224593}, {"source": 10, "target": 12, "value": 15.86309732728719}, {"source": 12, "target": 11, "value": 16.54023400834365}, {"source": 10, "target": 11, "value": 17.464713250981585}, {"source": 9, "target": 9, "value": 16.94058889435907}, {"source": 9, "target": 10, "value": 16.694017742871782}, {"source": 11, "target": 12, "value": 16.452418219732248}, {"source": 12, "target": 10, "value": 16.08615696278996}, {"source": 12, "target": 12, "value": 16.81153776021502}, {"source": 12, "target": 8, "value": 12.578608560737752}, {"source": 8, "target": 10, "value": 14.600725988091035}, {"source": 11, "target": 9, "value": 15.246777704369894}, {"source": 9, "target": 11, "value": 14.685077265027829}, {"source": 12, "target": 9, "value": 13.930460153846726}, {"source": 11, "target": 8, "value": 13.587894689529564}, {"source": 10, "target": 8, "value": 15.433813615108791}, {"source": 8, "target": 11, "value": 12.419960177847889}, {"source": 8, "target": 8, "value": 15.405307693308657}, {"source": 9, "target": 12, "value": 13.172114932533137}, {"source": 0, "target": 8, "value": 9.364134655008051}, {"source": 8, "target": 9, "value": 14.718693404419911}, {"source": 10, "target": 1, "value": 8.870364719583405}, {"source": 8, "target": 12, "value": 11.393390457443987}, {"source": 10, "target": 3, "value": 9.005624549193879}, {"source": 9, "target": 4, "value": 8.991521846075695}, {"source": 10, "target": 6, "value": 9.654636028527968}, {"source": 4, "target": 10, "value": 7.348728154231077}, {"source": 11, "target": 4, "value": 6.807354922057604}, {"source": 8, "target": 4, "value": 9.905387005018131}, {"source": 0, "target": 10, "value": 7.888743248898259}, {"source": 2, "target": 9, "value": 7.672425341971495}, {"source": 6, "target": 12, "value": 3.9068905956085187}, {"source": 11, "target": 5, "value": 6.727920454563199}, {"source": 2, "target": 10, "value": 7.321928094887363}, {"source": 5, "target": 10, "value": 7.3750394313469245}, {"source": 1, "target": 10, "value": 7.044394119358453}, {"source": 11, "target": 0, "value": 7.826548487290915}, {"source": 6, "target": 10, "value": 7.965784284662087}, {"source": 3, "target": 8, "value": 9.319672120946995}, {"source": 10, "target": 5, "value": 8.794415866350105}, {"source": 8, "target": 5, "value": 9.192292814470767}, {"source": 9, "target": 2, "value": 8.581200581924957}, {"source": 1, "target": 9, "value": 7.1799090900149345}, {"source": 12, "target": 2, "value": 5.78135971352466}, {"source": 12, "target": 1, "value": 6.714245517666122}, {"source": 9, "target": 6, "value": 9.08214904135387}, {"source": 10, "target": 4, "value": 8.820178962415188}, {"source": 10, "target": 2, "value": 8.661778097771988}, {"source": 9, "target": 3, "value": 8.707359132080883}, {"source": 10, "target": 0, "value": 9.211888294546004}, {"source": 4, "target": 9, "value": 7.721099188707186}, {"source": 8, "target": 0, "value": 9.709083812550343}, {"source": 12, "target": 6, "value": 6.7414669864011465}, {"source": 2, "target": 8, "value": 9.030667136246942}, {"source": 12, "target": 3, "value": 6.768184324776926}, {"source": 4, "target": 8, "value": 9.656424863277781}, {"source": 8, "target": 1, "value": 9.324180546618742}, {"source": 2, "target": 12, "value": 5.321928094887363}, {"source": 12, "target": 4, "value": 6.700439718141093}, {"source": 0, "target": 9, "value": 7.832890014164741}, {"source": 9, "target": 5, "value": 8.826548487290914}, {"source": 8, "target": 6, "value": 10.133142212400601}, {"source": 5, "target": 9, "value": 7.912889336229962}, {"source": 1, "target": 8, "value": 9.016808287686555}, {"source": 8, "target": 2, "value": 9.383704292474052}, {"source": 6, "target": 5, "value": 5.129283016944966}, {"source": 0, "target": 0, "value": 9.019590728357882}, {"source": 1, "target": 0, "value": 6.906890595608519}, {"source": 3, "target": 10, "value": 7.118941072723508}, {"source": 9, "target": 0, "value": 9.00842862207058}, {"source": 5, "target": 8, "value": 9.169925001442312}, {"source": 4, "target": 6, "value": 5.832890014164741}, {"source": 6, "target": 6, "value": 8.294620748891628}, {"source": 6, "target": 8, "value": 9.972979786066292}, {"source": 2, "target": 6, "value": 5.0}, {"source": 9, "target": 1, "value": 8.471675214392045}, {"source": 3, "target": 11, "value": 4.321928094887363}, {"source": 11, "target": 6, "value": 7.643856189774724}, {"source": 6, "target": 9, "value": 7.794415866350106}, {"source": 12, "target": 5, "value": 6.339850002884624}, {"source": 3, "target": 0, "value": 5.832890014164741}, {"source": 1, "target": 4, "value": 5.807354922057604}, {"source": 3, "target": 9, "value": 7.169925001442312}, {"source": 0, "target": 1, "value": 6.643856189774724}, {"source": 1, "target": 12, "value": 4.247927513443585}, {"source": 12, "target": 0, "value": 7.483815777264256}, {"source": 0, "target": 11, "value": 6.266786540694901}, {"source": 2, "target": 11, "value": 5.247927513443585}, {"source": 11, "target": 2, "value": 6.882643049361842}, {"source": 11, "target": 1, "value": 7.066089190457772}, {"source": 1, "target": 5, "value": 5.392317422778761}, {"source": 8, "target": 3, "value": 9.571752643503546}, {"source": 5, "target": 3, "value": 4.643856189774724}, {"source": 3, "target": 4, "value": 4.954196310386875}, {"source": 1, "target": 2, "value": 5.459431618637297}, {"source": 3, "target": 6, "value": 5.523561956057013}, {"source": 6, "target": 0, "value": 6.0}, {"source": 7, "target": 4, "value": 1.584962500721156}, {"source": 5, "target": 5, "value": 7.357552004618084}, {"source": 1, "target": 1, "value": 7.562242424221073}, {"source": 4, "target": 4, "value": 8.016808287686555}, {"source": 2, "target": 0, "value": 6.523561956057013}, {"source": 11, "target": 3, "value": 7.0}, {"source": 4, "target": 11, "value": 4.392317422778761}, {"source": 0, "target": 3, "value": 6.22881869049588}, {"source": 4, "target": 12, "value": 4.169925001442312}, {"source": 4, "target": 1, "value": 5.672425341971495}, {"source": 3, "target": 1, "value": 4.906890595608519}, {"source": 4, "target": 2, "value": 5.832890014164741}, {"source": 0, "target": 4, "value": 6.754887502163468}, {"source": 2, "target": 1, "value": 5.0}, {"source": 6, "target": 4, "value": 5.727920454563199}, {"source": 1, "target": 6, "value": 6.022367813028454}, {"source": 3, "target": 3, "value": 7.442943495848728}, {"source": 0, "target": 6, "value": 5.977279923499917}, {"source": 5, "target": 6, "value": 5.523561956057013}, {"source": 2, "target": 4, "value": 5.285402218862249}, {"source": 0, "target": 5, "value": 5.554588851677638}, {"source": 0, "target": 2, "value": 6.129283016944966}, {"source": 1, "target": 11, "value": 4.087462841250339}, {"source": 3, "target": 2, "value": 5.285402218862249}, {"source": 7, "target": 9, "value": 2.807354922057604}, {"source": 5, "target": 11, "value": 4.643856189774724}, {"source": 5, "target": 1, "value": 4.700439718141093}, {"source": 1, "target": 3, "value": 5.321928094887363}, {"source": 6, "target": 3, "value": 5.614709844115208}, {"source": 6, "target": 1, "value": 5.169925001442312}, {"source": 6, "target": 11, "value": 4.807354922057604}, {"source": 2, "target": 3, "value": 4.643856189774724}, {"source": 7, "target": 7, "value": 1.0}, {"source": 2, "target": 2, "value": 7.339850002884624}, {"source": 5, "target": 0, "value": 5.459431618637297}, {"source": 11, "target": 7, "value": 3.169925001442312}, {"source": 8, "target": 7, "value": 4.169925001442312}, {"source": 5, "target": 2, "value": 3.807354922057604}, {"source": 4, "target": 0, "value": 6.321928094887363}, {"source": 4, "target": 5, "value": 5.129283016944966}, {"source": 3, "target": 5, "value": 4.459431618637297}, {"source": 5, "target": 12, "value": 4.700439718141093}, {"source": 3, "target": 12, "value": 3.4594316186372973}, {"source": 5, "target": 4, "value": 4.954196310386875}, {"source": 4, "target": 3, "value": 5.321928094887363}, {"source": 0, "target": 12, "value": 5.20945336562895}, {"source": 0, "target": 7, "value": 2.0}, {"source": 7, "target": 8, "value": 3.321928094887362}, {"source": 6, "target": 2, "value": 4.700439718141093}, {"source": 7, "target": 0, "value": 1.0}, {"source": 2, "target": 5, "value": 4.392317422778761}, {"source": 9, "target": 7, "value": 3.0}, {"source": 10, "target": 7, "value": 1.0}, {"source": 7, "target": 3, "value": 0.0}]}